crc64fast/__init__.py
crc64fast/_lib.cpython-311-x86_64-linux-musl.so
crc64fast.libs/libgcc_s-2298274a.so.1
crc64fast-0.1.0.dist-info/METADATA
crc64fast-0.1.0.dist-info/WHEEL
crc64fast-0.1.0.dist-info/top_level.txt
crc64fast-0.1.0.dist-info/RECORD
crc64fast-0.1.0.dist-info/licenses/LICENSE-Apache
crc64fast-0.1.0.dist-info/licenses/LICENSE-MIT
