Metadata-Version: 2.4
Name: crc64fast
Version: 0.1.0
Summary: Python bindings for crc64fast-nvme Rust library
Author-email: Peter Lande <petelande@me.com>
License-Expression: MIT OR Apache-2.0
Project-URL: Homepage, https://github.com/Peter-Lande/python-crc64fast
Project-URL: Issues, https://github.com/Peter-Lande/python-crc64fast/issues
Classifier: Development Status :: 4 - Beta
Classifier: Programming Language :: Rust
Classifier: Operating System :: MacOS
Classifier: Operating System :: POSIX :: Linux
Classifier: Natural Language :: English
Classifier: Topic :: Software Development :: Libraries :: Python Modules
Requires-Python: >=3.9
License-File: LICENSE-Apache
License-File: LICENSE-MIT
Dynamic: license-file
